helper_clickhouse/__init__.py
helper_clickhouse-0.0.6.dist-info/DESCRIPTION.rst
helper_clickhouse-0.0.6.dist-info/METADATA
helper_clickhouse-0.0.6.dist-info/RECORD
helper_clickhouse-0.0.6.dist-info/WHEEL
helper_clickhouse-0.0.6.dist-info/metadata.json
helper_clickhouse-0.0.6.dist-info/top_level.txt
