Metadata-Version: 2.0
Name: helper-clickhouse
Version: 0.0.6
Summary: Clickhouse helper
Home-page: https://github.com/shuge/helper_clickhouse
Author: Shuge Lee
Author-email: shuge.lee@gmail.com
License: MIT License
Platform: UNKNOWN
